{"inkVersion":20,"root":[["ev","str","^Dungeon Master","/str",{"x()":"Name","exArgs":1},"out","/ev","\n","ev","str","^Pedro","/str",{"x()":"Icon","exArgs":1},"out","/ev","\n","^Muy bien parece que habéis derrotado a todos los enemigos","\n","^¿Seguís avanzando?","\n","ev","str","^Petra","/str",{"x()":"Name","exArgs":1},"out","/ev","\n","ev","str","^Petra","/str",{"x()":"Icon","exArgs":1},"out","/ev","\n","^No nos queda de otra","\n","^Sigamos avanzando por este terreno totalmente planeado","\n",["done",{"#f":5,"#n":"g-0"}],null],"done",{"#f":1}],"listDefs":{}}