{"inkVersion":20,"root":[["ev","str","^Dungeon Master","/str",{"x()":"Name","exArgs":1},"out","/ev","\n","ev","str","^Pedro","/str",{"x()":"Icon","exArgs":1},"out","/ev","\n","^Enhorabuena, habéis conseguido derrotar a todos los enemigos","\n","ev","str","^Petra","/str",{"x()":"Name","exArgs":1},"out","/ev","\n","ev","str","^Petra","/str",{"x()":"Icon","exArgs":1},"out","/ev","\n","^Que pena que haya terminado tan rápido","\n","ev","str","^Magnus","/str",{"x()":"Name","exArgs":1},"out","/ev","\n","ev","str","^Magnus","/str",{"x()":"Icon","exArgs":1},"out","/ev","\n","^ESA ES","\n","ev","str","^Dungeon Master","/str",{"x()":"Name","exArgs":1},"out","/ev","\n","ev","str","^Pedro","/str",{"x()":"Icon","exArgs":1},"out","/ev","\n","^Justo cuando derrotáis al último de los enemigos veis como una puerta al fondo de la habitación se abre, ¿Qué hacéis?","\n","ev","str","^Adel","/str",{"x()":"Name","exArgs":1},"out","/ev","\n","ev","str","^Adel","/str",{"x()":"Icon","exArgs":1},"out","/ev","\n","^¿Y NOSOTROS CUANDO JUGAMOS?","\n","ev","str","^Dungeon Master","/str",{"x()":"Name","exArgs":1},"out","/ev","\n","ev","str","^Pedro","/str",{"x()":"Icon","exArgs":1},"out","/ev","\n","^Espeeeera","\n","^Magnus, Petra ¿asumo que seguís adelante no?","\n","ev","str","^Magnus","/str",{"x()":"Name","exArgs":1},"out","/ev","\n","ev","str","^Magnus","/str",{"x()":"Icon","exArgs":1},"out","/ev","\n","^Claro que seguimos","\n","^Dale dale","\n","ev","str","^Dungeon Master","/str",{"x()":"Name","exArgs":1},"out","/ev","\n","ev","str","^Pedro","/str",{"x()":"Icon","exArgs":1},"out","/ev","\n","^Muy bien","\n","^En ese caso, avanzáis por la puerta decididos, pero sin saber muy bien que os depara el otro lado","\n",["done",{"#f":5,"#n":"g-0"}],null],"done",{"#f":1}],"listDefs":{}}